soundstream_light/__init__.py
soundstream_light/__main__.py
soundstream_light/_native.cpython-312-x86_64-linux-gnu.so
soundstream_light/api.py
soundstream_light/cli.py
soundstream_light/models.py
soundstream_light/runtime.py
soundstream_light-0.1.3.dist-info/METADATA
soundstream_light-0.1.3.dist-info/WHEEL
soundstream_light-0.1.3.dist-info/entry_points.txt
soundstream_light-0.1.3.dist-info/RECORD
soundstream_light-0.1.3.dist-info/licenses/LICENSE
