Metadata-Version: 2.2
Name: soundstream-light
Version: 0.1.3
Project-URL: Homepage, https://github.com/binbinsh/soundstream-light
Project-URL: Repository, https://github.com/binbinsh/soundstream-light
Requires-Python: >=3.10
Requires-Dist: typer>=0.12
Requires-Dist: rich>=13.7
Requires-Dist: numpy>=1.26
